newsapi/__init__.py
newsapi/const.py
newsapi/newsapi_auth.py
newsapi/newsapi_client.py
newsapi/newsapi_exception.py
newsapi/utils.py
newsapi_python-0.2.7.dist-info/LICENSE.txt
newsapi_python-0.2.7.dist-info/METADATA
newsapi_python-0.2.7.dist-info/WHEEL
newsapi_python-0.2.7.dist-info/top_level.txt
newsapi_python-0.2.7.dist-info/RECORD
